{"cameraMode":{"drawMode":0,"name":"Shaded","section":"Shading Mode"},"sceneLighting":true,"audioPlay":false,"sceneViewState":{"m_AlwaysRefresh":false,"showFog":true,"showSkybox":true,"showFlares":true,"showImageEffects":true,"showParticleSystems":true,"showVisualEffectGraphs":true,"m_FxEnabled":true},"in2DMode":false,"pivot":{"x":1.6495918035507203,"y":-4.456852912902832,"z":15.845952033996582},"rotation":{"x":0.2284373939037323,"y":-0.17384344339370728,"z":0.04151711240410805,"w":0.9570453763008118},"size":10.0,"orthographic":false}